README.md
setup.cfg
setup.py
levish/__init__.py
levish/shell.py
levish/utils.py
levish.egg-info/PKG-INFO
levish.egg-info/SOURCES.txt
levish.egg-info/dependency_links.txt
levish.egg-info/requires.txt
levish.egg-info/top_level.txt
levish/commands/__init__.py
levish/commands/basics.py