Metadata-Version: 2.1
Name: levish
Version: 0.1.8.0
Summary: Create your own shell.
Home-page: https://github.com/aaronlyy/levish
Author: Aaron Levi Can (aaronlyy)
Author-email: aaronlevican@gmail.com
License: MIT
Download-URL: https://github.com/aaronlyy/levish/archive/v0.1.8.0.tar.gz
Keywords: shell,terminal,commands,cmd,console
Platform: UNKNOWN
